sigma/__init__.py
sigma/__main__.py
sigma/app.py
sigma/backtest.py
sigma/charts.py
sigma/cli.py
sigma/comparison.py
sigma/config.py
sigma/llm.py
sigma/monitoring.py
sigma/portfolio.py
sigma/reporting.py
sigma/robustness.py
sigma/setup.py
sigma/strategy.py
sigma/tools.py
sigma/visualization.py
sigma/analytics/__init__.py
sigma/core/__init__.py
sigma/core/engine.py
sigma/core/intent.py
sigma/core/models.py
sigma/data/__init__.py
sigma/data/models.py
sigma/tools/backtest.py
sigma_terminal-3.3.2.dist-info/METADATA
sigma_terminal-3.3.2.dist-info/WHEEL
sigma_terminal-3.3.2.dist-info/entry_points.txt
sigma_terminal-3.3.2.dist-info/licenses/LICENSE
sigma_terminal-3.3.2.dist-info/RECORD
