Metadata-Version: 2.4
Name: sigma-terminal
Version: 3.3.2
Summary: Sigma - Finance Research Agent
Project-URL: Homepage, https://github.com/desenyon/sigma
Project-URL: Documentation, https://github.com/desenyon/sigma/wiki
Project-URL: Repository, https://github.com/desenyon/sigma
Author: Sigma Team
License: Proprietary
License-File: LICENSE
Keywords: ai,analytics,backtesting,finance,investment,macos,portfolio,quantitative,research,stocks,terminal,trading
Classifier: Development Status :: 4 - Beta
Classifier: Environment :: MacOS X
Classifier: Intended Audience :: Financial and Insurance Industry
Classifier: License :: Other/Proprietary License
Classifier: Operating System :: MacOS
Classifier: Programming Language :: Python :: 3.11
Classifier: Programming Language :: Python :: 3.12
Classifier: Topic :: Office/Business :: Financial :: Investment
Requires-Python: >=3.11
Requires-Dist: aiohttp>=3.9.0
Requires-Dist: anthropic>=0.18.0
Requires-Dist: google-genai>=1.0.0
Requires-Dist: groq>=0.4.0
Requires-Dist: httpx>=0.26.0
Requires-Dist: kaleido>=0.2.1
Requires-Dist: numpy>=1.26.0
Requires-Dist: openai>=1.12.0
Requires-Dist: pandas>=2.2.0
Requires-Dist: pillow>=10.2.0
Requires-Dist: plotext>=5.2.8
Requires-Dist: plotly>=5.18.0
Requires-Dist: pydantic-settings>=2.1.0
Requires-Dist: pydantic>=2.6.0
Requires-Dist: pyobjc-framework-cocoa>=10.0; sys_platform == 'darwin'
Requires-Dist: python-dotenv>=1.0.0
Requires-Dist: requests>=2.31.0
Requires-Dist: rich>=13.7.0
Requires-Dist: scipy>=1.12.0
Requires-Dist: textual>=0.47.0
Requires-Dist: yfinance>=0.2.36
Provides-Extra: all
Requires-Dist: black>=24.0.0; extra == 'all'
Requires-Dist: lean>=1.0.0; extra == 'all'
Requires-Dist: mypy>=1.8.0; extra == 'all'
Requires-Dist: py2app>=0.28.0; extra == 'all'
Requires-Dist: pytest-asyncio>=0.23.0; extra == 'all'
Requires-Dist: pytest>=8.0.0; extra == 'all'
Requires-Dist: ruff>=0.2.0; extra == 'all'
Provides-Extra: dev
Requires-Dist: black>=24.0.0; extra == 'dev'
Requires-Dist: mypy>=1.8.0; extra == 'dev'
Requires-Dist: py2app>=0.28.0; extra == 'dev'
Requires-Dist: pytest-asyncio>=0.23.0; extra == 'dev'
Requires-Dist: pytest>=8.0.0; extra == 'dev'
Requires-Dist: ruff>=0.2.0; extra == 'dev'
Provides-Extra: lean
Requires-Dist: lean>=1.0.0; extra == 'lean'
